pyghtml/__init__.py
pyghtml/attributes.py
pyghtml/py.typed
pyghtml/tags.py
pyghtml/utils.py
pyghtml-1.4.0.dist-info/METADATA
pyghtml-1.4.0.dist-info/WHEEL
pyghtml-1.4.0.dist-info/licenses/LICENSE.txt
pyghtml-1.4.0.dist-info/RECORD
