Metadata-Version: 2.4
Name: pyghtml
Version: 1.4.0
Summary: Python-Generatable HTML.
Project-URL: Homepage, https://github.com/shushtain/pyghtml
Project-URL: Issues, https://github.com/shushtain/pyghtml/issues
Author-email: Artem Shush <shushtain@gmail.com>
License-Expression: MIT
License-File: LICENSE.txt
Keywords: OOP,generator,html,python,static pages
Classifier: Intended Audience :: Developers
Classifier: License :: OSI Approved :: MIT License
Classifier: Natural Language :: English
Classifier: Operating System :: OS Independent
Classifier: Programming Language :: Python :: 3
Classifier: Topic :: Text Processing :: Markup :: HTML
Classifier: Typing :: Typed
Requires-Python: >=3.13
